{
    "FIREBASE_ADMIN_CREDENTIALS": "__FIREBASE_PLACEHOLDER__",
    "GOOGLE_OAUTH_CLIENT": "__GOOGLE_OAUTH_PLACEHOLDER__",
    "MILVUS_URI": "https://in03-955a82bbe424026.api.gcp-us-west1.zillizcloud.com",
    "MILVUS_TOKEN": "__MILVUS_TOKEN_PLACEHOLDER__",
    "MILVUS_COLLECTION": "internal_knowledge_assistant",
    "OPIK_API_KEY": "__OPIK_PLACEHOLDER__",
    "OPIK_PROJECT_NAME": "internal-knowledge-assistant",
    "OPIK_ENABLED": "true",
    "GOOGLE_PICKER_API_KEY": "REDACTED_GOOGLE_PICKER_API_KEY",
    "SECRET_KEY": "production-secret-key-change-me",
    "FIRESTORE_DB": "internal-knowledge-assistant"
}